{
  "generatedAt": "2026-06-04T10:06:04.686Z",
  "papers": [
    {
      "source": "papers",
      "sourceName": "QbitAI",
      "title": "连GitLab都开始裁程序员了",
      "url": "https://www.qbitai.com/2026/06/429117.html",
      "publishedAt": "2026-06-04T08:54:13.000Z",
      "summary": "硅谷科技公司Q1裁员同比增长40%"
    },
    {
      "source": "papers",
      "sourceName": "QbitAI",
      "title": "A股账户可以买Robotaxi了",
      "url": "https://www.qbitai.com/2026/06/428954.html",
      "publishedAt": "2026-06-04T07:41:33.000Z",
      "summary": "Robotaxi双雄同日官宣"
    },
    {
      "source": "papers",
      "sourceName": "QbitAI",
      "title": "英博数科亮相CCIG 2026，首次公开EBFlex私有化算力管理平台",
      "url": "https://www.qbitai.com/2026/06/428942.html",
      "publishedAt": "2026-06-04T07:25:26.000Z",
      "summary": "聚焦高校科研算力"
    },
    {
      "source": "papers",
      "sourceName": "QbitAI",
      "title": "比亚迪与中国石化深化战略合作 共建智慧能源生态",
      "url": "https://www.qbitai.com/2026/06/428933.html",
      "publishedAt": "2026-06-04T06:58:07.000Z",
      "summary": ""
    },
    {
      "source": "papers",
      "sourceName": "QbitAI",
      "title": "LeCun 10亿押注的方向，全球领先视觉大模型团队早已布局",
      "url": "https://www.qbitai.com/2026/06/428790.html",
      "publishedAt": "2026-06-04T03:43:37.000Z",
      "summary": "”隐空间世界模型很难，但我们一定要做“"
    },
    {
      "source": "papers",
      "sourceName": "QbitAI",
      "title": "一个GPT Plus会员的钱，够机器人跑一个月世界模型了",
      "url": "https://www.qbitai.com/2026/06/428791.html",
      "publishedAt": "2026-06-04T03:10:23.000Z",
      "summary": "不多不少，只要150"
    }
  ],
  "stats": {
    "paperItems": 6
  },
  "meta": {
    "sourceCount": 1
  }
}